agentica/__init__.py
agentica/__main__.py
agentica/agent.py
agentica/common.py
agentica/function.py
agentica/model_notices.py
agentica/template.py
agentica/version.py
agentica/agentica_client/agentica_client.py
agentica/agentica_client/global_csm.py
agentica/client_session_manager/__init__.py
agentica/client_session_manager/at_exit.py
agentica/client_session_manager/client_session_manager.py
agentica/coming_soon/__init__.py
agentica/coming_soon/coming_soon.py
agentica/decorator/__init__.py
agentica/decorator/decorator.py
agentica/demo/chat_with.py
agentica/demo/docs.md
agentica/demo/pitch.md
agentica/errors/__init__.py
agentica/flags/__init__.py
agentica/logging/__init__.py
agentica/logging/agent_listener.py
agentica/logging/agent_logger.py
agentica/logging/loggers/__init__.py
agentica/logging/loggers/file_logger.py
agentica/logging/loggers/print_logger.py
agentica/logging/loggers/standard_logger.py
agentica/logging/loggers/stream_logger.py
agentica/platform/__init__.py
agentica/sdk_logging/__init__.py
agentica/std/__init__.py
agentica/std/async_wrapper.py
agentica/std/caption.py
agentica/std/utils.py
agentica/std/web.py
agentica/unmcp/__init__.py
agentica/unmcp/mcp_function.py
agentica/unmcp/sigs.py
demos/__init__.py
demos/runner.py
demos/self-critic.py
demos/agents/captioned.py
demos/agents/chat.py
demos/agents/echo.py
demos/agents/follow-ups.py
demos/agents/simple-json.py
demos/agents/simple.py
demos/agents/sub-agents.py
demos/agents/templates.py
demos/agents/thinking-captions.py
demos/agents/threaded.py
demos/agents/threadpool.py
demos/agents/virtual-objects.py
demos/agents/web-search.py
demos/agents/deep_research/deepresearch.py
demos/functions/disconnect.py
demos/functions/echo.py
demos/functions/hello.py
demos/functions/json-mode.py
demos/functions/simple.py
demos/functions/slack.py
demos/functions/templates.py
demos/functions/web-test.py
symbolica_agentica-0.3.2.dist-info/licenses/LICENSE
symbolica_agentica-0.3.2.dist-info/METADATA
symbolica_agentica-0.3.2.dist-info/WHEEL
symbolica_agentica-0.3.2.dist-info/entry_points.txt
symbolica_agentica-0.3.2.dist-info/top_level.txt
symbolica_agentica-0.3.2.dist-info/RECORD
