Metadata-Version: 2.4
Name: symbolica-agentica
Version: 0.3.2
Summary: Agentica Python SDK
Project-URL: Homepage, https://www.symbolica.ai/agentica
Project-URL: Issues, https://github.com/symbolica-ai/agentica-issues
Requires-Python: <3.14.0,>=3.12.0
License-File: LICENSE
Requires-Dist: aiohttp>=3.12.15
Requires-Dist: dotenv>=0.9.9
Requires-Dist: fastmcp<=2.12.3
Requires-Dist: httpx>=0.28.1
Requires-Dist: websockets>=15.0.1
Requires-Dist: agentica-internal
Requires-Dist: opentelemetry-api>=1.20.0
Requires-Dist: opentelemetry-sdk>=1.20.0
Requires-Dist: opentelemetry-exporter-otlp-proto-grpc>=1.20.0
Requires-Dist: opentelemetry-instrumentation-httpx>=0.41b0
Requires-Dist: platformdirs>=4.5.0
Requires-Dist: rich>=14.2.0
Requires-Dist: prompt-toolkit>=3.0.52
Requires-Dist: pydantic>=2.12.4
Dynamic: license-file
